niwidgets/__init__.py
niwidgets/colormaps.py
niwidgets/controls.py
niwidgets/data/T1.nii.gz
niwidgets/data/cc400_roi_atlas.nii
niwidgets/data/cognitive control_pFgA_z.nii.gz
niwidgets/data/cognitive control_pFgA_z_FDR_0.01.nii.gz
niwidgets/data/example_surfaces/aparc.annot.ctab
niwidgets/data/example_surfaces/lh.aparc.annot
niwidgets/data/example_surfaces/lh.area
niwidgets/data/example_surfaces/lh.curv
niwidgets/data/example_surfaces/lh.inflated
niwidgets/data/example_surfaces/lh.thickness
niwidgets/data/streamlines.trk
niwidgets/exampledata.py
niwidgets/niwidget_surface.py
niwidgets/niwidget_volume.py
niwidgets/streamlines.py
niwidgets/version.py
niwidgets-0.2.2.dist-info/LICENSE.md
niwidgets-0.2.2.dist-info/WHEEL
niwidgets-0.2.2.dist-info/METADATA
niwidgets-0.2.2.dist-info/RECORD
