Metadata-Version: 2.1
Name: niwidgets
Version: 0.2.2
Summary: 'Interactive jupyter widgets for neuroimaging.'
Author: Jan Freyberg
Author-email: jan.freyberg@gmail.com
Requires-Python: >=3.5,<4.0
Classifier: Programming Language :: Python :: 3
Classifier: Programming Language :: Python :: 3.5
Classifier: Programming Language :: Python :: 3.6
Classifier: Programming Language :: Python :: 3.7
Requires-Dist: ipyvolume (>=0.5.1,<0.6.0)
Requires-Dist: ipywidgets (>=7.4,<8.0)
Requires-Dist: matplotlib (>=3.0,<4.0)
Requires-Dist: nibabel (>=2.4,<3.0)
Requires-Dist: nilearn (>=0.5.2,<0.6.0)
Requires-Dist: numpy (>=1.16,<2.0)
Requires-Dist: scikit-learn (>=0.20.3,<0.21.0)
Requires-Dist: scipy (>=1.2,<2.0)
